{
    "time_checks": {
      "reset": {
        "handler": "src.automation.routines.reset.ResetRoutine",
        "interval": 2700
      },
      "cleanup": {
        "handler": "src.automation.routines.cleanup.CleanupRoutine",
        "interval": 3600
      },
      "donate": {
        "handler": "src.automation.routines.allianceDonate.AllianceDonateRoutine",
        "interval": 25000
      },
      "help": {
        "handler": "src.automation.routines.help.HelpRoutine",
        "interval": 5
      },
      "dig": {
        "handler": "src.automation.routines.checkForDigs.CheckForDigsRoutine",
        "interval": 5
      },
      "secretary": {
        "handler": "src.automation.routines.secretary.SecretaryRoutine",
        "interval": 40
      },
      "mapExchange": {
        "handler": "src.automation.routines.mapExchange.MapExchangeRoutine",
        "interval": 300
      }
    },
    "scheduled_events": {
      "weekly_reset": {
        "handler": "src.automation.routines.weeklyReset.WeeklyResetRoutine",
        "schedule": {
          "day": null,
          "time": "01:50"
        }
      }
    }
  } 